LICENSE
README.md
setup.py
tiner/__init__.py
tiner/tiner.py
tiner/utils.py
tiner.egg-info/PKG-INFO
tiner.egg-info/SOURCES.txt
tiner.egg-info/dependency_links.txt
tiner.egg-info/requires.txt
tiner.egg-info/top_level.txt