Metadata-Version: 2.1
Name: tiner
Version: 0.0.8
Summary: Block-wise timer for Python
Home-page: https://github.com/gusye1234/tiner
Author: GustavoYe
License: UNKNOWN
Platform: UNKNOWN
Classifier: Programming Language :: Python :: 3
Classifier: License :: OSI Approved :: MIT License
Classifier: Operating System :: OS Independent
Requires-Python: >=3.6
